ben_cogs/__init__.py
ben_cogs/bot.py
ben_cogs/debug.py
ben_cogs/ie_jishaku.py
ben_cogs/misc.py
ben_cogs/sql.py
ben_cogs/stats.py
ben_cogs-0.15.2.dist-info/LICENSE
ben_cogs-0.15.2.dist-info/METADATA
ben_cogs-0.15.2.dist-info/WHEEL
ben_cogs-0.15.2.dist-info/top_level.txt
ben_cogs-0.15.2.dist-info/RECORD
